twn_solitaire/__init__.py
twn_solitaire/assets/Jellee-Roman/Jellee-Roman.otf
twn_solitaire/assets/Jellee-Roman/OFL-FAQ.txt
twn_solitaire/assets/Jellee-Roman/OFL.txt
twn_solitaire/config.py
twn_solitaire/constants.py
twn_solitaire/game.py
twn_solitaire/run.py
twn_solitaire-0.2.dist-info/METADATA
twn_solitaire-0.2.dist-info/WHEEL
twn_solitaire-0.2.dist-info/entry_points.txt
twn_solitaire-0.2.dist-info/RECORD
