Metadata-Version: 2.1
Name: twn-solitaire
Version: 0.2
Summary: Generic version of 2048 Solitaire. Simple, fun and satisfying game.
Home-page: https://github.com/geckon/2-n_solitaire
License: GNU GPL v3
Author: Tomáš Heger
Requires-Python: >=3.7,<4.0
Classifier: Intended Audience :: End Users/Desktop
Classifier: License :: OSI Approved :: GNU General Public License v3 (GPLv3)
Classifier: License :: Other/Proprietary License
Classifier: Natural Language :: English
Classifier: Operating System :: OS Independent
Classifier: Programming Language :: Python :: 3
Classifier: Programming Language :: Python :: 3.7
Classifier: Programming Language :: Python :: 3.8
Classifier: Programming Language :: Python :: 3.9
Classifier: Programming Language :: Python :: 3.10
Classifier: Programming Language :: Python :: 3.11
Classifier: Programming Language :: Python :: 3
Requires-Dist: pygame (>=2.2,<3.0)
Requires-Dist: toml (>=0.10.0,<0.11.0)
